htg_url/__init__.py
htg_url/apps.py
htg_url/generator.py
htg_url/sap.py
htg_url/tests.py
htg_url/views.py
htg_url/redis/__init__.py
htg_url/redis/client.py
htg_url/redis/__pycache__/__init__.cpython-38.pyc
htg_url/redis/__pycache__/client.cpython-38.pyc
htg_url_generator-0.2.dist-info/LICENCE.md
htg_url_generator-0.2.dist-info/METADATA
htg_url_generator-0.2.dist-info/WHEEL
htg_url_generator-0.2.dist-info/top_level.txt
htg_url_generator-0.2.dist-info/RECORD
