Metadata-Version: 2.1
Name: htg-url-generator
Version: 0.2
Summary: Generate hard to guess url from python secrets module. Implement custom view logic
Home-page: https://github.com/patsatsia/htg_url_generator
Author: Giorgi Patsatsia
Author-email: pats.giorgi@gmail.com
License: MIT
Platform: UNKNOWN
Classifier: Development Status :: 4 - Beta
Classifier: Environment :: Web Environment
Classifier: Intended Audience :: Developers
Classifier: License :: OSI Approved :: MIT License
Classifier: Operating System :: OS Independent
Classifier: Programming Language :: Python :: 3 :: Only
Classifier: Programming Language :: Python :: 3.8
Classifier: Programming Language :: Python :: Implementation :: CPython
Classifier: Topic :: Software Development :: Libraries :: Application Frameworks
Classifier: Topic :: Software Development :: Libraries :: Python Modules
Requires-Python: >=3.6
License-File: LICENCE.md
Requires-Dist: Django (>=3.1)
Requires-Dist: python-magic (>=0.4.0)
Requires-Dist: redis (>=4.0.0)
